auryn/__init__.py
auryn/__main__.py
auryn/api.py
auryn/cli.py
auryn/code.py
auryn/errors.py
auryn/gx.py
auryn/interpolate.py
auryn/origin.py
auryn/plugins/__init__.py
auryn/plugins/core.py
auryn/plugins/filesystem.py
auryn/py.typed
auryn/template.py
auryn/utils.py
auryn-1.0.3.dist-info/LICENSE
auryn-1.0.3.dist-info/METADATA
auryn-1.0.3.dist-info/WHEEL
auryn-1.0.3.dist-info/entry_points.txt
auryn-1.0.3.dist-info/RECORD
