Metadata-Version: 2.3
Name: auryn
Version: 1.0.3
Summary: The Auryn Metaprogramming Engine
Author: Dan Gittik
Author-email: dan.gittik@gmail.com
Requires-Python: >=3.10
Classifier: Programming Language :: Python :: 3
Classifier: Programming Language :: Python :: 3.10
Classifier: Programming Language :: Python :: 3.11
Classifier: Programming Language :: Python :: 3.12
Classifier: Programming Language :: Python :: 3.13
